helicone/async_logger/__init__.py
helicone/async_logger/async_logger.py
helicone/globals/__init__.py
helicone/globals/helicone.py
helicone/lock/__init__.py
helicone/openai_async/__init__.py
helicone/openai_async/openai_injector.py
helicone/openai_proxy/__init__.py
helicone/openai_proxy/openai_injector.py
helicone/requester/__init__.py
helicone/requirements.txt
helicone/runs/__init__.py
helicone/test.py
helicone-1.0.14.dist-info/LICENSE
helicone-1.0.14.dist-info/METADATA
helicone-1.0.14.dist-info/WHEEL
helicone-1.0.14.dist-info/RECORD
