Metadata-Version: 2.1
Name: helicone
Version: 1.0.14
Summary: A Python wrapper for the OpenAI API that logs all requests to Helicone.
Home-page: https://www.helicone.ai
License: Apache-2.0
Author: Helicone, Inc.
Author-email: help@helicone.ai
Requires-Python: >=3.8.1
Classifier: License :: OSI Approved :: Apache Software License
Classifier: Programming Language :: Python :: 3
Classifier: Programming Language :: Python :: 3.9
Classifier: Programming Language :: Python :: 3.10
Classifier: Programming Language :: Python :: 3.11
Requires-Dist: lockfile (>=0.12.2,<0.13.0)
Requires-Dist: openai (>=0.27.0,<0.28.0)
Requires-Dist: pyhumps (>=3.8.0,<4.0.0)
Project-URL: Repository, https://github.com/helicone/helicone/helicone-python
